openfund_client/__init__.py
openfund_client/api/__init__.py
openfund_client/api/auth/__init__.py
openfund_client/api/auth/refresh_token_api_v1_auth_refresh_post.py
openfund_client/api/auth/verify_token_api_v1_auth_verify_post.py
openfund_client/api/collect/__init__.py
openfund_client/api/collect/add_job_api_v_1_collcet_add_post.py
openfund_client/api/user/__init__.py
openfund_client/api/user/create_user_api_v1_user_post.py
openfund_client/api/user/get_user_list_api_v1_user_get.py
openfund_client/api/user/login_api_v1_user_login_post.py
openfund_client/client.py
openfund_client/errors.py
openfund_client/models/__init__.py
openfund_client/models/add_job_request.py
openfund_client/models/create_user_request.py
openfund_client/models/create_user_response_dto.py
openfund_client/models/get_user_list_response_dto.py
openfund_client/models/http_validation_error.py
openfund_client/models/login_request.py
openfund_client/models/login_response.py
openfund_client/models/refresh_token_request.py
openfund_client/models/refresh_token_response.py
openfund_client/models/validation_error.py
openfund_client/models/verify_token_request.py
openfund_client/py.typed
openfund_client/types.py
openfund_client-0.4.0.dist-info/METADATA
openfund_client-0.4.0.dist-info/WHEEL
openfund_client-0.4.0.dist-info/RECORD
